resume_extract/__init__.py
resume_extract/downloader.py
resume_extract/exceptions.py
resume_extract/extractor.py
resume_extract/langextract_integration.py
resume_extract/models.py
resume_extract/parsers.py
resume_extract-0.0.1.dist-info/METADATA
resume_extract-0.0.1.dist-info/WHEEL
resume_extract-0.0.1.dist-info/RECORD
