Metadata-Version: 2.4
Name: resume_extract
Version: 0.0.1
Summary: A library for extracting information contained in resumes
Project-URL: Homepage, https://github.com/hyunjin/resume-extract-py
Project-URL: Repository, https://github.com/hyunjin/resume-extract-py
Project-URL: Issues, https://github.com/hyunjin/resume-extract-py/issues
Author-email: hyunjin <leehj0110@kakao.com>
License: MIT
Keywords: ai,extract,langextract,parsing,resume
Classifier: Development Status :: 3 - Alpha
Classifier: Intended Audience :: Developers
Classifier: License :: OSI Approved :: MIT License
Classifier: Programming Language :: Python :: 3
Classifier: Programming Language :: Python :: 3.10
Classifier: Programming Language :: Python :: 3.11
Classifier: Programming Language :: Python :: 3.12
Requires-Python: >=3.10
Requires-Dist: beautifulsoup4>=4.11.0
Requires-Dist: email-validator>=2.3.0
Requires-Dist: langextract
Requires-Dist: lxml>=4.9.0
Requires-Dist: pydantic>=2.0.0
Requires-Dist: pypdf>=4.0.0
Requires-Dist: python-docx>=0.8.11
Requires-Dist: python-dotenv>=1.0.0
Requires-Dist: requests>=2.28.0
Requires-Dist: validators>=0.20.0
